umsg_gen/umsg_gen.py
umsg_gen/core/inc/umsg.h
umsg_gen/core/inc/umsg_port.h
umsg_gen/core/inc/umsg_types.h
umsg_gen/core/src/port_freertos.c
umsg_gen/core/src/port_posix.c
umsg_gen/core/src/umsg.c
umsg_gen/templates/CMakeLists.txt.j2
umsg_gen/templates/msg.c.j2
umsg_gen/templates/msg.h.j2
umsg_gen-0.1.15.dist-info/LICENSE
umsg_gen-0.1.15.dist-info/METADATA
umsg_gen-0.1.15.dist-info/WHEEL
umsg_gen-0.1.15.dist-info/entry_points.txt
umsg_gen-0.1.15.dist-info/top_level.txt
umsg_gen-0.1.15.dist-info/RECORD
